fishaudio/__init__.py
fishaudio/audiotools/__init__.py
fishaudio/audiotools/post.py
fishaudio/audiotools/preference.py
fishaudio/audiotools/core/__init__.py
fishaudio/audiotools/core/audio_signal.py
fishaudio/audiotools/core/display.py
fishaudio/audiotools/core/dsp.py
fishaudio/audiotools/core/effects.py
fishaudio/audiotools/core/ffmpeg.py
fishaudio/audiotools/core/loudness.py
fishaudio/audiotools/core/playback.py
fishaudio/audiotools/core/util.py
fishaudio/audiotools/core/whisper.py
fishaudio/audiotools/core/templates/__init__.py
fishaudio/audiotools/core/templates/headers.html
fishaudio/audiotools/core/templates/pandoc.css
fishaudio/audiotools/core/templates/widget.html
fishaudio/audiotools/data/__init__.py
fishaudio/audiotools/data/datasets.py
fishaudio/audiotools/data/preprocess.py
fishaudio/audiotools/data/transforms.py
fishaudio/audiotools/metrics/__init__.py
fishaudio/audiotools/metrics/distance.py
fishaudio/audiotools/metrics/quality.py
fishaudio/audiotools/metrics/spectral.py
fishaudio/audiotools/ml/__init__.py
fishaudio/audiotools/ml/accelerator.py
fishaudio/audiotools/ml/decorators.py
fishaudio/audiotools/ml/experiment.py
fishaudio/audiotools/ml/layers/__init__.py
fishaudio/audiotools/ml/layers/base.py
fishaudio/audiotools/ml/layers/spectral_gate.py
fishaudio/dac/__init__.py
fishaudio/dac/__main__.py
fishaudio/dac/compare/__init__.py
fishaudio/dac/compare/encodec.py
fishaudio/dac/model/__init__.py
fishaudio/dac/model/base.py
fishaudio/dac/model/dac.py
fishaudio/dac/model/discriminator.py
fishaudio/dac/nn/__init__.py
fishaudio/dac/nn/layers.py
fishaudio/dac/nn/loss.py
fishaudio/dac/nn/quantize.py
fishaudio/dac/utils/__init__.py
fishaudio/dac/utils/decode.py
fishaudio/dac/utils/encode.py
fishaudio/fish_speech/content_sequence.py
fishaudio/fish_speech/tokenizer.py
fishaudio/fish_speech/configs/base.yaml
fishaudio/fish_speech/configs/modded_dac_vq.yaml
fishaudio/fish_speech/configs/text2semantic_finetune.yaml
fishaudio-0.0.5.dist-info/LICENSE
fishaudio-0.0.5.dist-info/WHEEL
fishaudio-0.0.5.dist-info/METADATA
fishaudio-0.0.5.dist-info/RECORD
