Metadata-Version: 2.1
Name: fishaudio
Version: 0.0.5
Summary: text-to-speech synthesis 2
Author-email: calcuis <info@calcu.io>
Classifier: License :: OSI Approved :: MIT License
Requires-Dist: loguru
Requires-Dist: lightning
Requires-Dist: hydra-core
Requires-Dist: kui
Requires-Dist: loralib
Requires-Dist: tiktoken
Project-URL: GitHub, https://github.com/calcuis/text-to-speech-synthesis-2
Project-URL: Issues, https://github.com/calcuis/text-to-speech-synthesis-2/issues
